MANIFEST.in
README.md
setup.py
dash_flexbox_grid/Col.py
dash_flexbox_grid/Grid.py
dash_flexbox_grid/Row.py
dash_flexbox_grid/__init__.py
dash_flexbox_grid/_imports_.py
dash_flexbox_grid/dash_flexbox_grid.dev.js
dash_flexbox_grid/dash_flexbox_grid.min.js
dash_flexbox_grid/metadata.json
dash_flexbox_grid/package.json
dash_flexbox_grid/version.py
dash_flexbox_grid.egg-info/PKG-INFO
dash_flexbox_grid.egg-info/SOURCES.txt
dash_flexbox_grid.egg-info/dependency_links.txt
dash_flexbox_grid.egg-info/top_level.txt