Metadata-Version: 1.1
Name: dash-flexbox-grid
Version: 0.2.1
Summary: Wrapper around react-flexbox-grid for Plotly Dash
Home-page: UNKNOWN
Author: Sergei Pikhovkin s@pikhovkin.ru
Author-email: UNKNOWN
License: MIT
Platform: UNKNOWN
Classifier: Environment :: Web Environment
Classifier: License :: OSI Approved :: MIT License
Classifier: Programming Language :: Python :: 2.7
Classifier: Programming Language :: Python :: 3
